odoo/addons/hr_timesheet_analysis/README.rst
odoo/addons/hr_timesheet_analysis/__init__.py
odoo/addons/hr_timesheet_analysis/__manifest__.py
odoo/addons/hr_timesheet_analysis/i18n/de.po
odoo/addons/hr_timesheet_analysis/i18n/es.po
odoo/addons/hr_timesheet_analysis/i18n/fr.po
odoo/addons/hr_timesheet_analysis/i18n/hr_timesheet_analysis.pot
odoo/addons/hr_timesheet_analysis/i18n/it.po
odoo/addons/hr_timesheet_analysis/i18n/pt.po
odoo/addons/hr_timesheet_analysis/readme/CONTRIBUTORS.rst
odoo/addons/hr_timesheet_analysis/readme/DESCRIPTION.rst
odoo/addons/hr_timesheet_analysis/static/description/icon.png
odoo/addons/hr_timesheet_analysis/static/description/index.html
odoo/addons/hr_timesheet_analysis/views/account_analytic_line.xml
odoo12_addon_hr_timesheet_analysis-12.0.1.0.0.99.dev20.dist-info/METADATA
odoo12_addon_hr_timesheet_analysis-12.0.1.0.0.99.dev20.dist-info/WHEEL
odoo12_addon_hr_timesheet_analysis-12.0.1.0.0.99.dev20.dist-info/top_level.txt
odoo12_addon_hr_timesheet_analysis-12.0.1.0.0.99.dev20.dist-info/RECORD
